rgb_gradient/__init__.py
rgb_gradient/main.py
rgb_gradient-0.0.2.dist-info/LICENSE
rgb_gradient-0.0.2.dist-info/METADATA
rgb_gradient-0.0.2.dist-info/WHEEL
rgb_gradient-0.0.2.dist-info/top_level.txt
rgb_gradient-0.0.2.dist-info/RECORD
