Metadata-Version: 2.1
Name: rgb-gradient
Version: 0.0.2
Summary: Easily create gradients under the form of a list with given-input colors
Author-email: Ewan Humbert <xeway@protonmail.com>
License: GNU GENERAL PUBLIC LICENSE
Project-URL: Homepage, https://github.com/Xeway/rgb-gradient
Project-URL: Bug Tracker, https://github.com/Xeway/rgb-gradient/issues
Keywords: rgb,gradient,color,colors
Classifier: Programming Language :: Python :: 3
Classifier: Programming Language :: Python :: 3.9
Classifier: Programming Language :: Python :: 3.10
Classifier: License :: OSI Approved :: GNU General Public License v3 (GPLv3)
Classifier: Topic :: Software Development
Requires-Python: >=3.7
License-File: LICENSE
Requires-Dist: numpy
